trs_cli/__init__.py
trs_cli/client.py
trs_cli/errors.py
trs_cli/models.py
trs_cli-0.7.0.dist-info/LICENCE
trs_cli-0.7.0.dist-info/METADATA
trs_cli-0.7.0.dist-info/WHEEL
trs_cli-0.7.0.dist-info/top_level.txt
trs_cli-0.7.0.dist-info/RECORD
