Metadata-Version: 2.1
Name: trs-cli
Version: 0.7.0
Summary: GA4GH TRS Client
Home-page: https://github.com/elixir-cloud-aai/TRS-cli.git
Author: ELIXIR Cloud & AAI
Author-email: sarthakgupta072@gmail.com
License: Apache License 2.0
Keywords: ga4gh trs elixir rest restful api app server python
Platform: UNKNOWN
Classifier: License :: OSI Approved :: Apache Software License
Classifier: Development Status :: 3 - Alpha
Classifier: Intended Audience :: Science/Research
Classifier: Topic :: Scientific/Engineering :: Bio-Informatics
Classifier: Natural Language :: English
Classifier: Programming Language :: Python :: 3.6
Classifier: Programming Language :: Python :: 3.7
Classifier: Programming Language :: Python :: 3.8
Classifier: Programming Language :: Python :: 3.9
Requires-Python: >=3.6
License-File: LICENCE
Requires-Dist: pydantic (>=1.6.1)
Requires-Dist: requests (>=2.24.0)
Requires-Dist: requests-mock (>=1.8.0)
Requires-Dist: responses (>=0.12.0)
